redino
tests
