Metadata-Version: 1.0
Name: redino
Version: 2.0.1
Summary: redino
Home-page: UNKNOWN
Author: Bogdan Mustiata
Author-email: bogdan.mustiata@gmail.com
License: BSD
Platform: UNKNOWN
